instrubyte/__init__.py
instrubyte/commands/__init__.py
instrubyte/commands/init_cmd.py
instrubyte/commands/list_cmd.py
instrubyte/commands/main.py
instrubyte/commands/new_cmd.py
instrubyte/commands/run_cmd.py
instrubyte/core/base/base_instrument.py
instrubyte/core/base/base_lockin.py
instrubyte/core/base/base_smu.py
instrubyte/core/errors.py
instrubyte/core/sim/_template_engine.py
instrubyte/core/sim/backend.py
instrubyte/core/sim/dynamics.py
instrubyte/core/sim/yaml_spec.py
instrubyte/core/traits/__init__.py
instrubyte/core/traits/aux_outputs.py
instrubyte/core/types.py
instrubyte/discovery.py
instrubyte/duts/__init__.py
instrubyte/duts/base.py
instrubyte/duts/npn_transistor/__init__.py
instrubyte/duts/npn_transistor/model.py
instrubyte/instruments/__init__.py
instrubyte/instruments/keithley2400/__init__.py
instrubyte/instruments/keithley2400/driver.py
instrubyte/instruments/keithley2400/sim.yml
instrubyte/instruments/keithley2400/sim_plugin.py
instrubyte/instruments/sr844/__init__.py
instrubyte/instruments/sr844/driver.py
instrubyte/instruments/sr844/sim.yml
instrubyte/measurements/__init__.py
instrubyte-0.0.3.dist-info/METADATA
instrubyte-0.0.3.dist-info/WHEEL
instrubyte-0.0.3.dist-info/RECORD
