Metadata-Version: 2.1
Name: instrubyte
Version: 0.0.3
Summary: Lab instrument automation, simulation and data-logging
License: MIT
Author: Helin Cao
Author-email: helincao@gmail.com
Requires-Python: >=3.10,<4.0
Classifier: License :: OSI Approved :: MIT License
Classifier: Programming Language :: Python :: 3
Classifier: Programming Language :: Python :: 3.10
Classifier: Programming Language :: Python :: 3.11
Classifier: Programming Language :: Python :: 3.12
Classifier: Programming Language :: Python :: 3.13
Requires-Dist: jinja2 (>=3.1.6,<4.0.0)
Requires-Dist: jsonschema (>=4.23.0,<5.0.0)
Requires-Dist: pydantic (>=2.11.4,<3.0.0)
Requires-Dist: pytest (>=8.3.5,<9.0.0)
Requires-Dist: pyvisa (>=1.15.0,<2.0.0)
Requires-Dist: pyyaml (>=6.0.2,<7.0.0)
